{
  "rix0rrr": 1020,
  "mergify[bot]": 731,
  "eladb": 707,
  "dependabot-preview[bot]": 614,
  "skinny85": 436,
  "RomainMuller": 405,
  "njlynch": 356,
  "jogold": 321,
  "aws-cdk-automation": 316,
  "iliapolo": 254,
  "shivlaks": 237,
  "kaizencc": 224,
  "corymhall": 166,
  "otaviomacedo": 115,
  "NetaNir": 112,
  "madeline-k": 101,
  "robertd": 85,
  "peterwoodworth": 77,
  "comcalvi": 67,
  "dependabot[bot]": 65,
  "pahud": 61,
  "nija-at": 61,
  "hoegertn": 58,
  "nmussy": 56,
  "SoManyHs": 51,
  "BryanPan342": 46,
  "jumic": 46,
  "ayush987goyal": 46,
  "MrArnoldPalmer": 46,
  "ericzbeard": 44,
  "yamatatsu": 41,
  "piradeepk": 39,
  "BenChaimberg": 36,
  "SomayaB": 35,
  "Doug-AWS": 34,
  "mindstorms6": 34,
  "flemjame-at-amazon": 31,
  "Chriscbr": 31,
  "Jerry-AWS": 29,
  "TheRealAmazonKendra": 28,
  "misterjoshua": 24,
  "iamhopaul123": 23,
  "daschaa": 22,
  "moofish32": 21,
  "ryparker": 21,
  "NGL321": 21,
  "sam-goodwin": 21,
  "DaWyz": 19,
  "christophgysin": 17,
  "mpiroc": 17,
  "kylelaker": 16,
  "PatMyron": 16,
  "arcrank": 16,
  "blimmer": 15,
  "ddneilson": 15,
  "iRoachie": 15,
  "clareliguori": 13,
  "jungseoklee": 13,
  "zxkane": 13,
  "SeekerWing": 12,
  "rrhodes": 12,
  "Seiya6329": 12,
  "upparekh": 12,
  "workeitel": 12,
  "hencrice": 11,
  "markussiebert": 11,
  "tmokmss": 11,
  "civilizeddev": 10,
  "kellertk": 10,
  "watany-dev": 10,
  "neilkuan": 10,
  "nirvana124": 10,
  "cmckni3": 9,
  "dfezzie": 9,
  "hassanazharkhan": 9,
  "mrgrain": 9,
  "kirintwn": 9,
  "netroy": 9,
  "humanzz": 9,
  "otterley": 9,
  "CaerusKaru": 8,
  "duarten": 8,
  "Dzhuneyt": 8,
  "mprencipe": 8,
  "michaeldrey": 8,
  "Naumel": 8,
  "relm923": 8,
  "trivikr": 8,
  "hacker65536": 8,
  "sullis": 8,
  "DavidChristiansen": 7,
  "garnaat": 7,
  "mitchlloyd": 7,
  "tjenkinson": 7,
  "WinterYukky": 7,
  "bweigel": 7,
  "brentryan": 7,
  "DerkSchooltink": 7,
  "spg": 7,
  "ABevier": 6
}
