{
  "rix0rrr": 1223,
  "mergify[bot]": 958,
  "eladb": 707,
  "dependabot-preview[bot]": 614,
  "aws-cdk-automation": 498,
  "skinny85": 435,
  "RomainMuller": 419,
  "njlynch": 356,
  "kaizencc": 338,
  "jogold": 333,
  "iliapolo": 272,
  "corymhall": 256,
  "shivlaks": 237,
  "otaviomacedo": 158,
  "dependabot[bot]": 132,
  "madeline-k": 119,
  "NetaNir": 112,
  "comcalvi": 103,
  "robertd": 102,
  "pahud": 91,
  "MrArnoldPalmer": 91,
  "mrgrain": 90,
  "peterwoodworth": 85,
  "TheRealAmazonKendra": 79,
  "nija-at": 61,
  "lpizzinidev": 59,
  "hoegertn": 58,
  "jumic": 52,
  "watany-dev": 52,
  "SoManyHs": 51,
  "BryanPan342": 46,
  "ayush987goyal": 46,
  "ericzbeard": 44,
  "yamatatsu": 42,
  "piradeepk": 37,
  "BenChaimberg": 36,
  "SomayaB": 35,
  "Doug-AWS": 34,
  "mindstorms6": 34,
  "daschaa": 32,
  "flemjame-at-amazon": 31,
  "Chriscbr": 31,
  "colifran": 29,
  "kylelaker": 28,
  "misterjoshua": 25,
  "tmokmss": 25,
  "iamhopaul123": 23,
  "sumupitchayan": 23,
  "go-to-k": 22,
  "Naumel": 22,
  "moofish32": 21,
  "ryparker": 21,
  "WinterYukky": 20,
  "DaWyz": 19,
  "NGL321": 19,
  "iRoachie": 18,
  "PatMyron": 18,
  "sean-beath": 18,
  "christophgysin": 17,
  "mpiroc": 17,
  "nmussy": 17,
  "clareliguori": 16,
  "ddneilson": 16,
  "tam0ri": 16,
  "arcrank": 16,
  "blimmer": 15,
  "msambol": 15,
  "vinayak-kukreja": 15,
  "HBobertz": 14,
  "jungseoklee": 13,
  "zxkane": 13,
  "kellertk": 13,
  "clueleaf": 13,
  "humanzz": 13,
  "neilkuan": 13,
  "SeekerWing": 12,
  "rrhodes": 12,
  "Seiya6329": 12,
  "upparekh": 12,
  "workeitel": 12,
  "hencrice": 11,
  "markussiebert": 11,
  "civilizeddev": 10,
  "scanlonp": 10,
  "Tietew": 10,
  "Rizxcviii": 10,
  "otterley": 10,
  "nirvana124": 10,
  "CaerusKaru": 9,
  "cmckni3": 9,
  "hassanazharkhan": 9,
  "stevehouel": 9,
  "bun913": 9,
  "kirintwn": 9,
  "mikewrighton": 9,
  "netroy": 9,
  "DerkSchooltink": 9,
  "cecheta": 8,
  "duarten": 8,
  "Dzhuneyt": 8
}
